pygraphina-0.1.0.dist-info/METADATA
pygraphina-0.1.0.dist-info/WHEEL
pygraphina-0.1.0.dist-info/licenses/LICENSE
pygraphina/__init__.py
pygraphina/pygraphina.abi3.so
pygraphina-0.1.0.dist-info/RECORD
