Metadata-Version: 2.4
Name: pygraphina
Version: 0.1.0
Classifier: Programming Language :: Rust
Classifier: Programming Language :: Python :: Implementation :: CPython
Classifier: Programming Language :: Python :: Implementation :: PyPy
Classifier: Topic :: Software Development :: Libraries
Classifier: Topic :: Software Development :: Libraries :: Python Modules
Classifier: Topic :: Scientific/Engineering :: Information Analysis
Classifier: Topic :: Scientific/Engineering :: Mathematics
Classifier: Topic :: Scientific/Engineering :: Artificial Intelligence
License-File: LICENSE
Summary: Python bindings for the Graphina library
Keywords: graph-theory,data-science,graph-algorithms,graph-analytics
Author-email: Hassan Abedi <hassan.abedi.t@gmail.com>
Maintainer-email: Hassan Abedi <hassan.abedi.t@gmail.com>
License: MIT
Requires-Python: >=3.9
Project-URL: homepage, https://github.com/habedi/graphina
Project-URL: documentation, https://github.com/habedi/graphina
Project-URL: repository, https://github.com/habedi/graphina
